README.rst
setup.py
schoolbus/__init__.py
schoolbus/data.py
schoolbus/research_orgs.py
schoolbus.egg-info/PKG-INFO
schoolbus.egg-info/SOURCES.txt
schoolbus.egg-info/dependency_links.txt
schoolbus.egg-info/requires.txt
schoolbus.egg-info/top_level.txt