Metadata-Version: 1.0
Name: schoolbus
Version: 0.4.10
Summary: schoolbus is a library to guess whether an email is from an academic institution.
Home-page: https://github.com/benchling/schoolbus
Author: Joshua Ma
Author-email: josh@benchling.com
License: UNKNOWN
Platform: UNKNOWN
